<?xml version="1.0" encoding="UTF-8"?><unizh:homepage  xmlns="http://www.w3.org/1999/xhtml" xmlns:unizh="http://unizh.ch/doctypes/elements/1.0" xmlns:dc="http://purl.org/dc/elements/1.1/" xmlns:dcterms="http://purl.org/dc/terms/" xmlns:lenya="http://apache.org/cocoon/lenya/page-envelope/1.0" xmlns:xhtml="http://www.w3.org/1999/xhtml" unizh:tabs="false" dc:dummy="FIXME:keepNamespace" dcterms:dummy="FIXME:keepNamespace" lenya:dummy="FIXME:keepNamespace" xhtml:dummy="FIXME:keepNamespace">

	
<lenya:meta>
  <dc:title>Corporate Communication</dc:title>
  <dc:description>Abstract</dc:description>
  <dc:creator>Autor der Dokuments</dc:creator>
  <dc:subject>Keywords</dc:subject>
  <dc:publisher>Universität Zürich</dc:publisher>
  <dcterms:created>date of creation</dcterms:created>
  <dcterms:issued>date of publication</dcterms:issued>
  <dc:language>en</dc:language>
  <dc:rights>Universität Zürich</dc:rights>
</lenya:meta>
  <unizh:header>
    <unizh:superscription>University of Zurich</unizh:superscription>
    <unizh:heading>Publication title</unizh:heading>
  </unizh:header>
  <unizh:contcol1>
    <unizh:quicklinks label="Quick Links">
      <unizh:quicklink>
        <p>Topic</p>
        <xhtml:a href="#">Link</xhtml:a>
      </unizh:quicklink>
    </unizh:quicklinks>
  </unizh:contcol1>
  <unizh:related-content>
    <unizh:teaser>
      <unizh:title>Title</unizh:title>
      <p>Teaser text.</p>
    </unizh:teaser>
  </unizh:related-content>

<body>

<h2>The University and the General Public in Dialogue</h2>

<p>unicommunication (unicom) is responsible for promoting an
ongoing dialogue with the general public. It transmits
important information to the press and provides an accurate picture
of the University of Zurich to the general public.</p>

<p>unicommunication Online<br/>
 Gloriastrasse 18a<br/>
 8006 Zürich<br/>
 Tel. 01 634 41 58<br/>
 Fax 01 634 23 46<a href="mailto:online@unicom.unizh.ch"><br/>
 online@unicom.unizh.ch</a></p>
  </body>
</unizh:homepage>
